{
    "week": {
        "Company": "WBA", 
        "adj close": 4.944448, 
        "close": 50.624962, 
        "days": [
            {
                "Adj Close": 4.944448, 
                "Close": 50.624962, 
                "Company": "WBA", 
                "Date": "1995-06-16", 
                "High": 50.75, 
                "Low": 50.25, 
                "Open": 50.624962, 
                "Volume": 2216000, 
                "day": 5, 
                "week": 24
            }, 
            {
                "Adj Close": 4.907826, 
                "Close": 50.25, 
                "Company": "WBA", 
                "Date": "1995-06-15", 
                "High": 50.875038, 
                "Low": 50.124962, 
                "Open": 50.124962, 
                "Volume": 1568000, 
                "day": 4, 
                "week": 24
            }, 
            {
                "Adj Close": 4.895614, 
                "Close": 50.124962, 
                "Company": "WBA", 
                "Date": "1995-06-14", 
                "High": 50.124962, 
                "Low": 49.624962, 
                "Open": 49.875038, 
                "Volume": 1188800, 
                "day": 3, 
                "week": 24
            }, 
            {
                "Adj Close": 4.871204, 
                "Close": 49.875038, 
                "Company": "WBA", 
                "Date": "1995-06-13", 
                "High": 49.875038, 
                "Low": 48.375038, 
                "Open": 48.375038, 
                "Volume": 2538400, 
                "day": 2, 
                "week": 24
            }, 
            {
                "Adj Close": 4.71249, 
                "Close": 48.25, 
                "Company": "WBA", 
                "Date": "1995-06-12", 
                "High": 48.75, 
                "Low": 48.124962, 
                "Open": 48.624962, 
                "Volume": 1075200, 
                "day": 1, 
                "week": 24
            }
        ], 
        "first": 1, 
        "high": 50.875038, 
        "last": 5, 
        "low": 48.124962, 
        "open": 48.624962, 
        "volume": 8586400, 
        "week": 24, 
        "year": 1995
    }
}