{
    "week": {
        "Company": "SUNS",
        "adj close": 14.042474,
        "close": 16.76,
        "days": [
            {
                "Adj Close": 14.042474,
                "Close": 16.76,
                "Company": "SUNS",
                "Date": "2014-05-30",
                "High": 16.940001,
                "Low": 16.42,
                "Open": 16.9,
                "Volume": 69100,
                "day": 5,
                "week": 22
            },
            {
                "Adj Close": 14.101123,
                "Close": 16.83,
                "Company": "SUNS",
                "Date": "2014-05-29",
                "High": 17.200001,
                "Low": 16.780001,
                "Open": 17.139999,
                "Volume": 39200,
                "day": 4,
                "week": 22
            },
            {
                "Adj Close": 14.251938,
                "Close": 17.01,
                "Company": "SUNS",
                "Date": "2014-05-28",
                "High": 17.110001,
                "Low": 16.860001,
                "Open": 17.110001,
                "Volume": 22800,
                "day": 3,
                "week": 22
            },
            {
                "Adj Close": 14.444644,
                "Close": 17.24,
                "Company": "SUNS",
                "Date": "2014-05-27",
                "High": 17.48,
                "Low": 17.049999,
                "Open": 17.48,
                "Volume": 47300,
                "day": 2,
                "week": 22
            }
        ],
        "first": 2,
        "high": 17.48,
        "last": 5,
        "low": 16.42,
        "open": 17.48,
        "volume": 178400,
        "week": 22,
        "year": 2014
    }
}