{
    "month": {
        "Company": "FANG", 
        "adj close": 33.77, 
        "close": 33.77, 
        "days": [
            {
                "Adj Close": 33.77, 
                "Close": 33.77, 
                "Company": "FANG", 
                "Date": "2013-05-31", 
                "High": 35.23, 
                "Low": 33.669998, 
                "Open": 34.630001, 
                "Volume": 596800, 
                "day": 31, 
                "month": 5
            }, 
            {
                "Adj Close": 34.950001, 
                "Close": 34.950001, 
                "Company": "FANG", 
                "Date": "2013-05-30", 
                "High": 35.650002, 
                "Low": 34.400002, 
                "Open": 34.779999, 
                "Volume": 355500, 
                "day": 30, 
                "month": 5
            }, 
            {
                "Adj Close": 34.959999, 
                "Close": 34.959999, 
                "Company": "FANG", 
                "Date": "2013-05-29", 
                "High": 35.310001, 
                "Low": 34.310001, 
                "Open": 34.810001, 
                "Volume": 230000, 
                "day": 29, 
                "month": 5
            }, 
            {
                "Adj Close": 34.950001, 
                "Close": 34.950001, 
                "Company": "FANG", 
                "Date": "2013-05-28", 
                "High": 35.91, 
                "Low": 34.310001, 
                "Open": 34.77, 
                "Volume": 383300, 
                "day": 28, 
                "month": 5
            }, 
            {
                "Adj Close": 34.32, 
                "Close": 34.32, 
                "Company": "FANG", 
                "Date": "2013-05-24", 
                "High": 34.669998, 
                "Low": 32.77, 
                "Open": 33.389999, 
                "Volume": 792300, 
                "day": 24, 
                "month": 5
            }, 
            {
                "Adj Close": 33.27, 
                "Close": 33.27, 
                "Company": "FANG", 
                "Date": "2013-05-23", 
                "High": 34.299999, 
                "Low": 31.52, 
                "Open": 31.98, 
                "Volume": 609700, 
                "day": 23, 
                "month": 5
            }, 
            {
                "Adj Close": 32.540001, 
                "Close": 32.540001, 
                "Company": "FANG", 
                "Date": "2013-05-22", 
                "High": 34.84, 
                "Low": 31.870001, 
                "Open": 32.25, 
                "Volume": 876400, 
                "day": 22, 
                "month": 5
            }, 
            {
                "Adj Close": 31.709999, 
                "Close": 31.709999, 
                "Company": "FANG", 
                "Date": "2013-05-21", 
                "High": 32.400002, 
                "Low": 31.23, 
                "Open": 32.400002, 
                "Volume": 295800, 
                "day": 21, 
                "month": 5
            }, 
            {
                "Adj Close": 32.029999, 
                "Close": 32.029999, 
                "Company": "FANG", 
                "Date": "2013-05-20", 
                "High": 32.25, 
                "Low": 31.24, 
                "Open": 31.620001, 
                "Volume": 545100, 
                "day": 20, 
                "month": 5
            }, 
            {
                "Adj Close": 31.43, 
                "Close": 31.43, 
                "Company": "FANG", 
                "Date": "2013-05-17", 
                "High": 32.41, 
                "Low": 30.200001, 
                "Open": 30.52, 
                "Volume": 914000, 
                "day": 17, 
                "month": 5
            }, 
            {
                "Adj Close": 29.940001, 
                "Close": 29.940001, 
                "Company": "FANG", 
                "Date": "2013-05-16", 
                "High": 31.6, 
                "Low": 29.73, 
                "Open": 31.17, 
                "Volume": 3939200, 
                "day": 16, 
                "month": 5
            }, 
            {
                "Adj Close": 29.48, 
                "Close": 29.48, 
                "Company": "FANG", 
                "Date": "2013-05-15", 
                "High": 29.77, 
                "Low": 27.190001, 
                "Open": 28.290001, 
                "Volume": 599000, 
                "day": 15, 
                "month": 5
            }, 
            {
                "Adj Close": 28.870001, 
                "Close": 28.870001, 
                "Company": "FANG", 
                "Date": "2013-05-14", 
                "High": 28.91, 
                "Low": 28.530001, 
                "Open": 28.610001, 
                "Volume": 73700, 
                "day": 14, 
                "month": 5
            }, 
            {
                "Adj Close": 28.66, 
                "Close": 28.66, 
                "Company": "FANG", 
                "Date": "2013-05-13", 
                "High": 29.0, 
                "Low": 28.35, 
                "Open": 28.459999, 
                "Volume": 51700, 
                "day": 13, 
                "month": 5
            }, 
            {
                "Adj Close": 28.58, 
                "Close": 28.58, 
                "Company": "FANG", 
                "Date": "2013-05-10", 
                "High": 28.700001, 
                "Low": 27.91, 
                "Open": 28.65, 
                "Volume": 89400, 
                "day": 10, 
                "month": 5
            }, 
            {
                "Adj Close": 28.68, 
                "Close": 28.68, 
                "Company": "FANG", 
                "Date": "2013-05-09", 
                "High": 29.67, 
                "Low": 28.469999, 
                "Open": 29.57, 
                "Volume": 189700, 
                "day": 9, 
                "month": 5
            }, 
            {
                "Adj Close": 29.530001, 
                "Close": 29.530001, 
                "Company": "FANG", 
                "Date": "2013-05-08", 
                "High": 29.75, 
                "Low": 27.51, 
                "Open": 28.379999, 
                "Volume": 200900, 
                "day": 8, 
                "month": 5
            }, 
            {
                "Adj Close": 28.540001, 
                "Close": 28.540001, 
                "Company": "FANG", 
                "Date": "2013-05-07", 
                "High": 28.809999, 
                "Low": 27.879999, 
                "Open": 28.709999, 
                "Volume": 264200, 
                "day": 7, 
                "month": 5
            }, 
            {
                "Adj Close": 28.76, 
                "Close": 28.76, 
                "Company": "FANG", 
                "Date": "2013-05-06", 
                "High": 29.4, 
                "Low": 27.58, 
                "Open": 27.58, 
                "Volume": 393000, 
                "day": 6, 
                "month": 5
            }, 
            {
                "Adj Close": 27.48, 
                "Close": 27.48, 
                "Company": "FANG", 
                "Date": "2013-05-03", 
                "High": 27.66, 
                "Low": 27.16, 
                "Open": 27.440001, 
                "Volume": 86000, 
                "day": 3, 
                "month": 5
            }, 
            {
                "Adj Close": 27.1, 
                "Close": 27.1, 
                "Company": "FANG", 
                "Date": "2013-05-02", 
                "High": 27.25, 
                "Low": 26.459999, 
                "Open": 26.459999, 
                "Volume": 168400, 
                "day": 2, 
                "month": 5
            }, 
            {
                "Adj Close": 26.440001, 
                "Close": 26.440001, 
                "Company": "FANG", 
                "Date": "2013-05-01", 
                "High": 27.01, 
                "Low": 25.950001, 
                "Open": 26.1, 
                "Volume": 347100, 
                "day": 1, 
                "month": 5
            }
        ], 
        "first": 121, 
        "high": 35.91, 
        "last": 151, 
        "low": 25.950001, 
        "month": 5, 
        "open": 26.1, 
        "volume": 12001200, 
        "year": 2013
    }
}