{
    "week": {
        "Company": "MDLZ", 
        "adj close": 16.855384, 
        "close": 29.58, 
        "days": [
            {
                "Adj Close": 16.855384, 
                "Close": 29.58, 
                "Company": "MDLZ", 
                "Date": "2010-01-15", 
                "High": 30.0, 
                "Low": 28.1, 
                "Open": 28.41, 
                "Volume": 25979600, 
                "day": 5, 
                "week": 2
            }, 
            {
                "Adj Close": 16.593266, 
                "Close": 29.120001, 
                "Company": "MDLZ", 
                "Date": "2010-01-14", 
                "High": 29.59, 
                "Low": 28.73, 
                "Open": 29.450001, 
                "Volume": 10023700, 
                "day": 4, 
                "week": 2
            }, 
            {
                "Adj Close": 16.655946, 
                "Close": 29.23, 
                "Company": "MDLZ", 
                "Date": "2010-01-13", 
                "High": 30.1, 
                "Low": 29.16, 
                "Open": 29.709999, 
                "Volume": 18000100, 
                "day": 3, 
                "week": 2
            }, 
            {
                "Adj Close": 16.690136, 
                "Close": 29.290001, 
                "Company": "MDLZ", 
                "Date": "2010-01-12", 
                "High": 29.34, 
                "Low": 28.639999, 
                "Open": 28.75, 
                "Volume": 19561000, 
                "day": 2, 
                "week": 2
            }, 
            {
                "Adj Close": 16.410922, 
                "Close": 28.799999, 
                "Company": "MDLZ", 
                "Date": "2010-01-11", 
                "High": 29.1, 
                "Low": 28.629999, 
                "Open": 28.98, 
                "Volume": 11819700, 
                "day": 1, 
                "week": 2
            }
        ], 
        "first": 0, 
        "high": 30.1, 
        "last": 5, 
        "low": 28.1, 
        "open": 0, 
        "volume": 85384100, 
        "week": 2, 
        "year": 2010
    }
}