{
    "month": {
        "Company": "SUNS",
        "adj close": 14.585816,
        "close": 18.24,
        "days": [
            {
                "Adj Close": 14.585816,
                "Close": 18.24,
                "Company": "SUNS",
                "Date": "2013-10-31",
                "High": 18.51,
                "Low": 18.15,
                "Open": 18.5,
                "Volume": 31100,
                "day": 31,
                "month": 10
            },
            {
                "Adj Close": 14.449874,
                "Close": 18.07,
                "Company": "SUNS",
                "Date": "2013-10-30",
                "High": 18.42,
                "Low": 18.07,
                "Open": 18.309999,
                "Volume": 39600,
                "day": 30,
                "month": 10
            },
            {
                "Adj Close": 14.889688,
                "Close": 18.620001,
                "Company": "SUNS",
                "Date": "2013-10-29",
                "High": 18.799999,
                "Low": 18.51,
                "Open": 18.610001,
                "Volume": 27700,
                "day": 29,
                "month": 10
            },
            {
                "Adj Close": 14.881691,
                "Close": 18.610001,
                "Company": "SUNS",
                "Date": "2013-10-28",
                "High": 18.91,
                "Low": 18.469999,
                "Open": 18.82,
                "Volume": 30700,
                "day": 28,
                "month": 10
            },
            {
                "Adj Close": 15.089603,
                "Close": 18.870001,
                "Company": "SUNS",
                "Date": "2013-10-25",
                "High": 18.98,
                "Low": 18.629999,
                "Open": 18.76,
                "Volume": 17600,
                "day": 25,
                "month": 10
            },
            {
                "Adj Close": 14.993643,
                "Close": 18.75,
                "Company": "SUNS",
                "Date": "2013-10-24",
                "High": 18.75,
                "Low": 18.690001,
                "Open": 18.73,
                "Volume": 26500,
                "day": 24,
                "month": 10
            },
            {
                "Adj Close": 14.929671,
                "Close": 18.67,
                "Company": "SUNS",
                "Date": "2013-10-23",
                "High": 18.75,
                "Low": 18.530001,
                "Open": 18.620001,
                "Volume": 25800,
                "day": 23,
                "month": 10
            },
            {
                "Adj Close": 14.945664,
                "Close": 18.690001,
                "Company": "SUNS",
                "Date": "2013-10-22",
                "High": 18.75,
                "Low": 18.65,
                "Open": 18.709999,
                "Volume": 32400,
                "day": 22,
                "month": 10
            },
            {
                "Adj Close": 14.876092,
                "Close": 18.719999,
                "Company": "SUNS",
                "Date": "2013-10-21",
                "High": 18.85,
                "Low": 18.700001,
                "Open": 18.84,
                "Volume": 29100,
                "day": 21,
                "month": 10
            },
            {
                "Adj Close": 14.971452,
                "Close": 18.84,
                "Company": "SUNS",
                "Date": "2013-10-18",
                "High": 18.85,
                "Low": 18.68,
                "Open": 18.82,
                "Volume": 29700,
                "day": 18,
                "month": 10
            },
            {
                "Adj Close": 14.820466,
                "Close": 18.65,
                "Company": "SUNS",
                "Date": "2013-10-17",
                "High": 18.75,
                "Low": 18.530001,
                "Open": 18.57,
                "Volume": 36200,
                "day": 17,
                "month": 10
            },
            {
                "Adj Close": 14.820466,
                "Close": 18.65,
                "Company": "SUNS",
                "Date": "2013-10-16",
                "High": 18.790001,
                "Low": 18.549999,
                "Open": 18.690001,
                "Volume": 24200,
                "day": 16,
                "month": 10
            },
            {
                "Adj Close": 14.820466,
                "Close": 18.65,
                "Company": "SUNS",
                "Date": "2013-10-15",
                "High": 18.75,
                "Low": 18.290001,
                "Open": 18.620001,
                "Volume": 28800,
                "day": 15,
                "month": 10
            },
            {
                "Adj Close": 14.733054,
                "Close": 18.540001,
                "Company": "SUNS",
                "Date": "2013-10-14",
                "High": 18.889999,
                "Low": 18.23,
                "Open": 18.780001,
                "Volume": 44200,
                "day": 14,
                "month": 10
            },
            {
                "Adj Close": 14.963506,
                "Close": 18.83,
                "Company": "SUNS",
                "Date": "2013-10-11",
                "High": 18.83,
                "Low": 18.450001,
                "Open": 18.48,
                "Volume": 27500,
                "day": 11,
                "month": 10
            },
            {
                "Adj Close": 14.756893,
                "Close": 18.57,
                "Company": "SUNS",
                "Date": "2013-10-10",
                "High": 18.57,
                "Low": 18.370001,
                "Open": 18.48,
                "Volume": 30300,
                "day": 10,
                "month": 10
            },
            {
                "Adj Close": 14.582068,
                "Close": 18.35,
                "Company": "SUNS",
                "Date": "2013-10-09",
                "High": 18.5,
                "Low": 18.219999,
                "Open": 18.360001,
                "Volume": 26200,
                "day": 9,
                "month": 10
            },
            {
                "Adj Close": 14.510548,
                "Close": 18.26,
                "Company": "SUNS",
                "Date": "2013-10-08",
                "High": 18.389999,
                "Low": 18.129999,
                "Open": 18.35,
                "Volume": 36500,
                "day": 8,
                "month": 10
            },
            {
                "Adj Close": 14.518495,
                "Close": 18.27,
                "Company": "SUNS",
                "Date": "2013-10-07",
                "High": 18.379999,
                "Low": 17.92,
                "Open": 17.92,
                "Volume": 28100,
                "day": 7,
                "month": 10
            },
            {
                "Adj Close": 14.303935,
                "Close": 18.0,
                "Company": "SUNS",
                "Date": "2013-10-04",
                "High": 18.129999,
                "Low": 17.719999,
                "Open": 17.719999,
                "Volume": 14800,
                "day": 4,
                "month": 10
            },
            {
                "Adj Close": 14.089376,
                "Close": 17.73,
                "Company": "SUNS",
                "Date": "2013-10-03",
                "High": 17.98,
                "Low": 17.700001,
                "Open": 17.83,
                "Volume": 19000,
                "day": 3,
                "month": 10
            },
            {
                "Adj Close": 14.160896,
                "Close": 17.82,
                "Company": "SUNS",
                "Date": "2013-10-02",
                "High": 18.290001,
                "Low": 17.6,
                "Open": 18.18,
                "Volume": 116900,
                "day": 2,
                "month": 10
            },
            {
                "Adj Close": 14.478761,
                "Close": 18.219999,
                "Company": "SUNS",
                "Date": "2013-10-01",
                "High": 18.34,
                "Low": 17.98,
                "Open": 18.08,
                "Volume": 17200,
                "day": 1,
                "month": 10
            }
        ],
        "first": 274,
        "high": 18.98,
        "last": 304,
        "low": 17.6,
        "month": 10,
        "open": 18.08,
        "volume": 740100,
        "year": 2013
    }
}