{
    "week": {
        "Company": "TROW", 
        "adj close": 12.11159, 
        "close": 32.700001, 
        "days": [
            {
                "Adj Close": 12.11159, 
                "Close": 32.700001, 
                "Company": "TROW", 
                "Date": "2002-07-05", 
                "High": 32.889999, 
                "Low": 30.950001, 
                "Open": 31.02, 
                "Volume": 641400, 
                "day": 5, 
                "week": 27
            }, 
            {
                "Adj Close": 11.48564, 
                "Close": 31.01, 
                "Company": "TROW", 
                "Date": "2002-07-03", 
                "High": 31.67, 
                "Low": 30.440001, 
                "Open": 31.309999, 
                "Volume": 916000, 
                "day": 3, 
                "week": 27
            }, 
            {
                "Adj Close": 11.600459, 
                "Close": 31.32, 
                "Company": "TROW", 
                "Date": "2002-07-02", 
                "High": 32.16, 
                "Low": 31.1, 
                "Open": 32.150002, 
                "Volume": 1240000, 
                "day": 2, 
                "week": 27
            }, 
            {
                "Adj Close": 11.867136, 
                "Close": 32.040001, 
                "Company": "TROW", 
                "Date": "2002-07-01", 
                "High": 33.619999, 
                "Low": 31.950001, 
                "Open": 32.900002, 
                "Volume": 1283800, 
                "day": 1, 
                "week": 27
            }
        ], 
        "first": 1, 
        "high": 33.619999, 
        "last": 5, 
        "low": 30.440001, 
        "open": 32.900002, 
        "volume": 4081200, 
        "week": 27, 
        "year": 2002
    }
}