{
    "week": {
        "Company": "LPLA",
        "adj close": 41.022749,
        "close": 42.490002,
        "days": [
            {
                "Adj Close": 41.022749,
                "Close": 42.490002,
                "Company": "LPLA",
                "Date": "2015-01-23",
                "High": 43.119999,
                "Low": 42.470001,
                "Open": 42.880001,
                "Volume": 519200,
                "day": 5,
                "week": 4
            },
            {
                "Adj Close": 41.563409,
                "Close": 43.049999,
                "Company": "LPLA",
                "Date": "2015-01-22",
                "High": 43.189999,
                "Low": 41.450001,
                "Open": 41.880001,
                "Volume": 511200,
                "day": 4,
                "week": 4
            },
            {
                "Adj Close": 40.288991,
                "Close": 41.73,
                "Company": "LPLA",
                "Date": "2015-01-21",
                "High": 41.84,
                "Low": 40.560001,
                "Open": 41.02,
                "Volume": 614600,
                "day": 3,
                "week": 4
            },
            {
                "Adj Close": 39.622819,
                "Close": 41.040001,
                "Company": "LPLA",
                "Date": "2015-01-20",
                "High": 41.439999,
                "Low": 40.23,
                "Open": 41.439999,
                "Volume": 1019800,
                "day": 2,
                "week": 4
            }
        ],
        "first": 0,
        "high": 43.189999,
        "last": 5,
        "low": 40.23,
        "open": 0,
        "volume": 2664800,
        "week": 4,
        "year": 2015
    }
}