{
    "month": {
        "Company": "TROW", 
        "adj close": 73.459472, 
        "close": 78.400002, 
        "days": [
            {
                "Adj Close": 73.459472, 
                "Close": 78.400002, 
                "Company": "TROW", 
                "Date": "2014-09-30", 
                "High": 78.900002, 
                "Low": 78.059998, 
                "Open": 78.769997, 
                "Volume": 1345400, 
                "day": 30, 
                "month": 9
            }, 
            {
                "Adj Close": 73.571906, 
                "Close": 78.519997, 
                "Company": "TROW", 
                "Date": "2014-09-29", 
                "High": 78.690002, 
                "Low": 77.919998, 
                "Open": 78.57, 
                "Volume": 1399500, 
                "day": 29, 
                "month": 9
            }, 
            {
                "Adj Close": 74.209055, 
                "Close": 79.199997, 
                "Company": "TROW", 
                "Date": "2014-09-26", 
                "High": 79.489998, 
                "Low": 78.529999, 
                "Open": 78.669998, 
                "Volume": 1259200, 
                "day": 26, 
                "month": 9
            }, 
            {
                "Adj Close": 73.759307, 
                "Close": 78.720001, 
                "Company": "TROW", 
                "Date": "2014-09-25", 
                "High": 79.68, 
                "Low": 78.519997, 
                "Open": 79.589996, 
                "Volume": 2444900, 
                "day": 25, 
                "month": 9
            }, 
            {
                "Adj Close": 74.668181, 
                "Close": 79.690002, 
                "Company": "TROW", 
                "Date": "2014-09-24", 
                "High": 79.739998, 
                "Low": 79.019997, 
                "Open": 79.349998, 
                "Volume": 1670300, 
                "day": 24, 
                "month": 9
            }, 
            {
                "Adj Close": 74.059141, 
                "Close": 79.040001, 
                "Company": "TROW", 
                "Date": "2014-09-23", 
                "High": 79.650002, 
                "Low": 78.940002, 
                "Open": 79.089996, 
                "Volume": 1498500, 
                "day": 23, 
                "month": 9
            }, 
            {
                "Adj Close": 74.19969, 
                "Close": 79.190002, 
                "Company": "TROW", 
                "Date": "2014-09-22", 
                "High": 80.080002, 
                "Low": 79.169998, 
                "Open": 80.07, 
                "Volume": 1306900, 
                "day": 22, 
                "month": 9
            }, 
            {
                "Adj Close": 75.024232, 
                "Close": 80.07, 
                "Company": "TROW", 
                "Date": "2014-09-19", 
                "High": 80.739998, 
                "Low": 79.5, 
                "Open": 80.5, 
                "Volume": 1487700, 
                "day": 19, 
                "month": 9
            }, 
            {
                "Adj Close": 75.155409, 
                "Close": 80.209999, 
                "Company": "TROW", 
                "Date": "2014-09-18", 
                "High": 80.529999, 
                "Low": 79.559998, 
                "Open": 79.629997, 
                "Volume": 918100, 
                "day": 18, 
                "month": 9
            }, 
            {
                "Adj Close": 74.302759, 
                "Close": 79.300003, 
                "Company": "TROW", 
                "Date": "2014-09-17", 
                "High": 79.769997, 
                "Low": 78.779999, 
                "Open": 79.599998, 
                "Volume": 1224500, 
                "day": 17, 
                "month": 9
            }, 
            {
                "Adj Close": 74.096621, 
                "Close": 79.080002, 
                "Company": "TROW", 
                "Date": "2014-09-16", 
                "High": 79.239998, 
                "Low": 78.419998, 
                "Open": 78.739998, 
                "Volume": 1353800, 
                "day": 16, 
                "month": 9
            }, 
            {
                "Adj Close": 74.002924, 
                "Close": 78.980003, 
                "Company": "TROW", 
                "Date": "2014-09-15", 
                "High": 79.720001, 
                "Low": 78.699997, 
                "Open": 79.550003, 
                "Volume": 1271000, 
                "day": 15, 
                "month": 9
            }, 
            {
                "Adj Close": 74.508889, 
                "Close": 79.519997, 
                "Company": "TROW", 
                "Date": "2014-09-12", 
                "High": 80.07, 
                "Low": 79.18, 
                "Open": 79.809998, 
                "Volume": 1461700, 
                "day": 12, 
                "month": 9
            }, 
            {
                "Adj Close": 74.715026, 
                "Close": 79.739998, 
                "Company": "TROW", 
                "Date": "2014-09-11", 
                "High": 79.879997, 
                "Low": 79.239998, 
                "Open": 79.5, 
                "Volume": 1495400, 
                "day": 11, 
                "month": 9
            }, 
            {
                "Adj Close": 74.705654, 
                "Close": 80.169998, 
                "Company": "TROW", 
                "Date": "2014-09-10", 
                "High": 80.720001, 
                "Low": 79.940002, 
                "Open": 80.489998, 
                "Volume": 1493400, 
                "day": 10, 
                "month": 9
            }, 
            {
                "Adj Close": 74.919981, 
                "Close": 80.400002, 
                "Company": "TROW", 
                "Date": "2014-09-09", 
                "High": 80.900002, 
                "Low": 80.129997, 
                "Open": 80.900002, 
                "Volume": 1221400, 
                "day": 9, 
                "month": 9
            }, 
            {
                "Adj Close": 75.488404, 
                "Close": 81.010002, 
                "Company": "TROW", 
                "Date": "2014-09-08", 
                "High": 81.150002, 
                "Low": 80.720001, 
                "Open": 80.910004, 
                "Volume": 946000, 
                "day": 8, 
                "month": 9
            }, 
            {
                "Adj Close": 75.637495, 
                "Close": 81.169998, 
                "Company": "TROW", 
                "Date": "2014-09-05", 
                "High": 81.18, 
                "Low": 80.290001, 
                "Open": 80.790001, 
                "Volume": 761400, 
                "day": 5, 
                "month": 9
            }, 
            {
                "Adj Close": 75.45113, 
                "Close": 80.970001, 
                "Company": "TROW", 
                "Date": "2014-09-04", 
                "High": 81.309998, 
                "Low": 80.669998, 
                "Open": 80.970001, 
                "Volume": 803600, 
                "day": 4, 
                "month": 9
            }, 
            {
                "Adj Close": 75.152941, 
                "Close": 80.650002, 
                "Company": "TROW", 
                "Date": "2014-09-03", 
                "High": 81.489998, 
                "Low": 80.510002, 
                "Open": 81.089996, 
                "Volume": 831800, 
                "day": 3, 
                "month": 9
            }, 
            {
                "Adj Close": 75.208849, 
                "Close": 80.709999, 
                "Company": "TROW", 
                "Date": "2014-09-02", 
                "High": 81.5, 
                "Low": 80.470001, 
                "Open": 81.190002, 
                "Volume": 1469100, 
                "day": 2, 
                "month": 9
            }
        ], 
        "first": 245, 
        "high": 81.5, 
        "last": 273, 
        "low": 77.919998, 
        "month": 9, 
        "open": 81.190002, 
        "volume": 27663600, 
        "year": 2014
    }
}