{
    "week": {
        "Company": "SONA",
        "adj close": 6.705801,
        "close": 7.75,
        "days": [
            {
                "Adj Close": 6.705801,
                "Close": 7.75,
                "Company": "SONA",
                "Date": "2008-08-08",
                "High": 7.75,
                "Low": 7.72,
                "Open": 7.72,
                "Volume": 2000,
                "day": 5,
                "week": 32
            },
            {
                "Adj Close": 6.671191,
                "Close": 7.71,
                "Company": "SONA",
                "Date": "2008-08-07",
                "High": 7.73,
                "Low": 7.27,
                "Open": 7.6,
                "Volume": 1100,
                "day": 4,
                "week": 32
            },
            {
                "Adj Close": 6.662538,
                "Close": 7.7,
                "Company": "SONA",
                "Date": "2008-08-06",
                "High": 7.73,
                "Low": 7.7,
                "Open": 7.73,
                "Volume": 600,
                "day": 3,
                "week": 32
            },
            {
                "Adj Close": 6.697148,
                "Close": 7.74,
                "Company": "SONA",
                "Date": "2008-08-05",
                "High": 7.75,
                "Low": 7.74,
                "Open": 7.75,
                "Volume": 1300,
                "day": 2,
                "week": 32
            },
            {
                "Adj Close": 6.662538,
                "Close": 7.7,
                "Company": "SONA",
                "Date": "2008-08-04",
                "High": 7.72,
                "Low": 7.5,
                "Open": 7.72,
                "Volume": 2200,
                "day": 1,
                "week": 32
            }
        ],
        "first": 1,
        "high": 7.75,
        "last": 5,
        "low": 7.27,
        "open": 7.72,
        "volume": 7200,
        "week": 32,
        "year": 2008
    }
}