{
    "week": {
        "Company": "PIH",
        "adj close": 8.5,
        "close": 8.5,
        "days": [
            {
                "Adj Close": 8.5,
                "Close": 8.5,
                "Company": "PIH",
                "Date": "2014-08-15",
                "High": 8.618,
                "Low": 8.48,
                "Open": 8.5,
                "Volume": 61800,
                "day": 5,
                "week": 33
            },
            {
                "Adj Close": 8.7,
                "Close": 8.7,
                "Company": "PIH",
                "Date": "2014-08-14",
                "High": 8.71,
                "Low": 8.58,
                "Open": 8.59,
                "Volume": 15700,
                "day": 4,
                "week": 33
            },
            {
                "Adj Close": 8.56,
                "Close": 8.56,
                "Company": "PIH",
                "Date": "2014-08-13",
                "High": 8.66,
                "Low": 8.52,
                "Open": 8.63,
                "Volume": 14700,
                "day": 3,
                "week": 33
            },
            {
                "Adj Close": 8.61,
                "Close": 8.61,
                "Company": "PIH",
                "Date": "2014-08-12",
                "High": 8.65,
                "Low": 8.6,
                "Open": 8.6,
                "Volume": 8900,
                "day": 2,
                "week": 33
            },
            {
                "Adj Close": 8.61,
                "Close": 8.61,
                "Company": "PIH",
                "Date": "2014-08-11",
                "High": 8.69,
                "Low": 8.6,
                "Open": 8.62,
                "Volume": 16900,
                "day": 1,
                "week": 33
            }
        ],
        "first": 1,
        "high": 8.71,
        "last": 5,
        "low": 8.48,
        "open": 8.62,
        "volume": 118000,
        "week": 33,
        "year": 2014
    }
}