{
    "week": {
        "Company": "TROW", 
        "adj close": 25.800631, 
        "close": 31.51, 
        "days": [
            {
                "Adj Close": 25.800631, 
                "Close": 31.51, 
                "Company": "TROW", 
                "Date": "2008-11-14", 
                "High": 34.029999, 
                "Low": 31.299999, 
                "Open": 31.809999, 
                "Volume": 2722500, 
                "day": 5, 
                "week": 46
            }, 
            {
                "Adj Close": 26.684944, 
                "Close": 32.59, 
                "Company": "TROW", 
                "Date": "2008-11-13", 
                "High": 32.669998, 
                "Low": 28.59, 
                "Open": 32.189999, 
                "Volume": 7306400, 
                "day": 4, 
                "week": 46
            }, 
            {
                "Adj Close": 26.095403, 
                "Close": 31.870001, 
                "Company": "TROW", 
                "Date": "2008-11-12", 
                "High": 33.560001, 
                "Low": 31.860001, 
                "Open": 32.599998, 
                "Volume": 2655000, 
                "day": 3, 
                "week": 46
            }, 
            {
                "Adj Close": 27.069784, 
                "Close": 33.060001, 
                "Company": "TROW", 
                "Date": "2008-11-11", 
                "High": 34.939999, 
                "Low": 32.5, 
                "Open": 34.939999, 
                "Volume": 3087700, 
                "day": 2, 
                "week": 46
            }, 
            {
                "Adj Close": 28.944852, 
                "Close": 35.349998, 
                "Company": "TROW", 
                "Date": "2008-11-10", 
                "High": 37.240002, 
                "Low": 34.84, 
                "Open": 36.540001, 
                "Volume": 2711000, 
                "day": 1, 
                "week": 46
            }
        ], 
        "first": 1, 
        "high": 37.240002, 
        "last": 5, 
        "low": 28.59, 
        "open": 36.540001, 
        "volume": 18482600, 
        "week": 46, 
        "year": 2008
    }
}