{
    "week": {
        "Company": "TROW", 
        "adj close": 73.238548, 
        "close": 79.82, 
        "days": [
            {
                "Adj Close": 73.238548, 
                "Close": 79.82, 
                "Company": "TROW", 
                "Date": "2013-12-06", 
                "High": 80.129997, 
                "Low": 79.519997, 
                "Open": 80.0, 
                "Volume": 1582900, 
                "day": 5, 
                "week": 49
            }, 
            {
                "Adj Close": 72.06409, 
                "Close": 78.540001, 
                "Company": "TROW", 
                "Date": "2013-12-05", 
                "High": 79.730003, 
                "Low": 78.480003, 
                "Open": 79.580002, 
                "Volume": 1044700, 
                "day": 4, 
                "week": 49
            }, 
            {
                "Adj Close": 72.990814, 
                "Close": 79.550003, 
                "Company": "TROW", 
                "Date": "2013-12-04", 
                "High": 80.32, 
                "Low": 78.779999, 
                "Open": 79.519997, 
                "Volume": 753800, 
                "day": 3, 
                "week": 49
            }, 
            {
                "Adj Close": 73.100915, 
                "Close": 79.669998, 
                "Company": "TROW", 
                "Date": "2013-12-03", 
                "High": 80.510002, 
                "Low": 79.410004, 
                "Open": 80.349998, 
                "Volume": 1062500, 
                "day": 2, 
                "week": 49
            }, 
            {
                "Adj Close": 74.036816, 
                "Close": 80.690002, 
                "Company": "TROW", 
                "Date": "2013-12-02", 
                "High": 81.459999, 
                "Low": 80.470001, 
                "Open": 80.650002, 
                "Volume": 1154400, 
                "day": 1, 
                "week": 49
            }
        ], 
        "first": 1, 
        "high": 81.459999, 
        "last": 5, 
        "low": 78.480003, 
        "open": 80.650002, 
        "volume": 5598300, 
        "week": 49, 
        "year": 2013
    }
}