{
    "month": {
        "Company": "LPLA",
        "adj close": 43.550409,
        "close": 44.860001,
        "days": [
            {
                "Adj Close": 43.550409,
                "Close": 44.860001,
                "Company": "LPLA",
                "Date": "2015-02-27",
                "High": 45.23,
                "Low": 44.740002,
                "Open": 44.84,
                "Volume": 426500,
                "day": 27,
                "month": 2
            },
            {
                "Adj Close": 43.657198,
                "Close": 44.970001,
                "Company": "LPLA",
                "Date": "2015-02-26",
                "High": 45.459999,
                "Low": 44.759998,
                "Open": 45.27,
                "Volume": 496200,
                "day": 26,
                "month": 2
            },
            {
                "Adj Close": 43.890187,
                "Close": 45.459999,
                "Company": "LPLA",
                "Date": "2015-02-25",
                "High": 45.799999,
                "Low": 45.25,
                "Open": 45.48,
                "Volume": 516700,
                "day": 25,
                "month": 2
            },
            {
                "Adj Close": 44.006046,
                "Close": 45.580002,
                "Company": "LPLA",
                "Date": "2015-02-24",
                "High": 46.23,
                "Low": 45.400002,
                "Open": 45.75,
                "Volume": 681100,
                "day": 24,
                "month": 2
            },
            {
                "Adj Close": 43.928807,
                "Close": 45.5,
                "Company": "LPLA",
                "Date": "2015-02-23",
                "High": 45.740002,
                "Low": 44.830002,
                "Open": 45.669998,
                "Volume": 577400,
                "day": 23,
                "month": 2
            },
            {
                "Adj Close": 44.112245,
                "Close": 45.689999,
                "Company": "LPLA",
                "Date": "2015-02-20",
                "High": 45.799999,
                "Low": 43.919998,
                "Open": 45.279999,
                "Volume": 857400,
                "day": 20,
                "month": 2
            },
            {
                "Adj Close": 43.359181,
                "Close": 44.91,
                "Company": "LPLA",
                "Date": "2015-02-19",
                "High": 47.380001,
                "Low": 44.25,
                "Open": 47.060001,
                "Volume": 1739200,
                "day": 19,
                "month": 2
            },
            {
                "Adj Close": 43.3978,
                "Close": 44.950001,
                "Company": "LPLA",
                "Date": "2015-02-18",
                "High": 45.810001,
                "Low": 44.490002,
                "Open": 45.560001,
                "Volume": 1379800,
                "day": 18,
                "month": 2
            },
            {
                "Adj Close": 44.179827,
                "Close": 45.759998,
                "Company": "LPLA",
                "Date": "2015-02-17",
                "High": 45.970001,
                "Low": 45.349998,
                "Open": 45.5,
                "Volume": 681800,
                "day": 17,
                "month": 2
            },
            {
                "Adj Close": 44.025352,
                "Close": 45.599998,
                "Company": "LPLA",
                "Date": "2015-02-13",
                "High": 45.830002,
                "Low": 45.259998,
                "Open": 45.419998,
                "Volume": 334900,
                "day": 13,
                "month": 2
            },
            {
                "Adj Close": 43.890187,
                "Close": 45.459999,
                "Company": "LPLA",
                "Date": "2015-02-12",
                "High": 45.939999,
                "Low": 45.0,
                "Open": 45.310001,
                "Volume": 380700,
                "day": 12,
                "month": 2
            },
            {
                "Adj Close": 43.446073,
                "Close": 45.0,
                "Company": "LPLA",
                "Date": "2015-02-11",
                "High": 45.349998,
                "Low": 44.720001,
                "Open": 44.869999,
                "Volume": 223600,
                "day": 11,
                "month": 2
            },
            {
                "Adj Close": 43.446073,
                "Close": 45.0,
                "Company": "LPLA",
                "Date": "2015-02-10",
                "High": 45.110001,
                "Low": 44.369999,
                "Open": 44.919998,
                "Volume": 348700,
                "day": 10,
                "month": 2
            },
            {
                "Adj Close": 42.847484,
                "Close": 44.380001,
                "Company": "LPLA",
                "Date": "2015-02-09",
                "High": 45.0,
                "Low": 44.150002,
                "Open": 44.509998,
                "Volume": 392800,
                "day": 9,
                "month": 2
            },
            {
                "Adj Close": 43.301251,
                "Close": 44.849998,
                "Company": "LPLA",
                "Date": "2015-02-06",
                "High": 45.290001,
                "Low": 43.669998,
                "Open": 44.049999,
                "Volume": 733800,
                "day": 6,
                "month": 2
            },
            {
                "Adj Close": 42.142692,
                "Close": 43.650002,
                "Company": "LPLA",
                "Date": "2015-02-05",
                "High": 43.880001,
                "Low": 42.619999,
                "Open": 42.799999,
                "Volume": 255200,
                "day": 5,
                "month": 2
            },
            {
                "Adj Close": 41.186877,
                "Close": 42.66,
                "Company": "LPLA",
                "Date": "2015-02-04",
                "High": 43.189999,
                "Low": 42.599998,
                "Open": 42.700001,
                "Volume": 318500,
                "day": 4,
                "month": 2
            },
            {
                "Adj Close": 41.293079,
                "Close": 42.77,
                "Company": "LPLA",
                "Date": "2015-02-03",
                "High": 42.82,
                "Low": 41.610001,
                "Open": 41.830002,
                "Volume": 739400,
                "day": 3,
                "month": 2
            },
            {
                "Adj Close": 40.018661,
                "Close": 41.450001,
                "Company": "LPLA",
                "Date": "2015-02-02",
                "High": 42.040001,
                "Low": 41.150002,
                "Open": 41.419998,
                "Volume": 736700,
                "day": 2,
                "month": 2
            }
        ],
        "first": 33,
        "high": 47.380001,
        "last": 58,
        "low": 41.150002,
        "month": 2,
        "open": 41.419998,
        "volume": 11820400,
        "year": 2015
    }
}